pyformatting/__init__.py
pyformatting/base_formatter.py
pyformatting/correct_version.py
pyformatting/default_format.py
pyformatting/format_38.py
pyformatting/formatter.py
pyformatting/helpers.py
pyformatting/optional_format.py
pyformatting-0.3.3.dist-info/LICENSE
pyformatting-0.3.3.dist-info/METADATA
pyformatting-0.3.3.dist-info/WHEEL
pyformatting-0.3.3.dist-info/top_level.txt
pyformatting-0.3.3.dist-info/RECORD
