Metadata-Version: 2.1
Name: pyformatting
Version: 0.3.3
Summary: Pyformatting is a collection of useful formatting features.
Home-page: https://github.com/0dminnimda/pyformatting
Author: 0dminnimda
Author-email: 0dminnimda.contact@gmail.com
License: MIT
Project-URL: Documentation, https://pyformatting.readthedocs.io/en/latest/
Project-URL: Say Thanks!, https://saythanks.io/to/0dminnimda.contact%40gmail.com
Project-URL: Bug tracker, https://github.com/0dminnimda/pyformatting/issues
Keywords: format, formatting, formatter,python format, python formatting, python formatter,optional format, optional formatting, optional formatter,default format, default formatting, default formatter
Platform: UNKNOWN
Classifier: Development Status :: 3 - Alpha
Classifier: Intended Audience :: Developers
Classifier: License :: OSI Approved :: MIT License
Classifier: Operating System :: OS Independent
Classifier: Programming Language :: Python :: 3
Classifier: Programming Language :: Python :: 3.1
Classifier: Programming Language :: Python :: 3.2
Classifier: Programming Language :: Python :: 3.3
Classifier: Programming Language :: Python :: 3.4
Classifier: Programming Language :: Python :: 3.5
Classifier: Programming Language :: Python :: 3.6
Classifier: Programming Language :: Python :: 3.7
Classifier: Programming Language :: Python :: 3.8
Classifier: Topic :: Software Development :: Libraries :: Python Modules
Classifier: Topic :: Utilities
Requires-Python: ~=3.1
